Metadata-Version: 1.0
Name: django-postit
Version: 0.3
Summary: django-postit is a scrumboard application for django projects
Home-page: http://github.com/0xPr0xy/django-postit
Author: 0xPr0xy
Author-email: 0xPr0xy@gmail.com
License: BSD
Download-URL: http://github.com/0xPr0xy/django-postit/downloads
Platform: UNKNOWN
Classifier: Environment :: Web Environment
Classifier: Intended Audience :: Developers
Classifier: License :: OSI Approved :: BSD License
Classifier: Operating System :: OS Independent
Classifier: Programming Language :: Python
Classifier: Framework :: Django
